README.md
setup.py
./__init__.py
./excel_fast_load.py
excel_fast_load.egg-info/PKG-INFO
excel_fast_load.egg-info/SOURCES.txt
excel_fast_load.egg-info/dependency_links.txt
excel_fast_load.egg-info/requires.txt
excel_fast_load.egg-info/top_level.txt