Metadata-Version: 2.1
Name: excel-fast-load
Version: 1.0.0
Summary: Alternate, faster version of pandas.read_excel by Felix Kling
Home-page: https://github.com/ScienceForChange/excel_fast_load
Author: Felix Kling
Author-email: felix@felix-kling.de
License: None
Platform: UNKNOWN
Classifier: Programming Language :: Python :: 3
Classifier: Programming Language :: Python :: 3.7
Classifier: Development Status :: 4 - Beta
